django_mtg_res/__init__.py
django_mtg_res/admin.py
django_mtg_res/apps.py
django_mtg_res/models.py
django_mtg_res/tests.py
django_mtg_res/views.py
django_mtg_res/migrations/0001_initial.py
django_mtg_res/migrations/0002_requestlog_remote_addr.py
django_mtg_res/migrations/__init__.py
django_mtg_res/utils/__init__.py
django_mtg_res-0.1.5.dist-info/licenses/LICENSE
django_mtg_res-0.1.5.dist-info/METADATA
django_mtg_res-0.1.5.dist-info/WHEEL
django_mtg_res-0.1.5.dist-info/top_level.txt
django_mtg_res-0.1.5.dist-info/RECORD
