Metadata-Version: 2.4
Name: django-mtg-res
Version: 0.1.5
Summary: A Django app for logging HTTP requests and responses
Author-email: Rio Cheung <mtg.rio.cheung@gmail.com>
Maintainer-email: Rio Cheung <mtg.rio.cheung@gmail.com>
Project-URL: Homepage, https://github.com/yourusername/django-mtg-res
Project-URL: Repository, https://github.com/yourusername/django-mtg-res
Project-URL: Issues, https://github.com/yourusername/django-mtg-res/issues
Project-URL: Changelog, https://github.com/yourusername/django-mtg-res/blob/main/CHANGELOG.md
Keywords: django,logging,requests,http,api
Classifier: Development Status :: 4 - Beta
Classifier: Environment :: Web Environment
Classifier: Framework :: Django
Classifier: Framework :: Django :: 4.0
Classifier: Framework :: Django :: 4.1
Classifier: Framework :: Django :: 4.2
Classifier: Framework :: Django :: 5.0
Classifier: Framework :: Django :: 5.1
Classifier: Framework :: Django :: 5.2
Classifier: Intended Audience :: Developers
Classifier: Operating System :: OS Independent
Classifier: Programming Language :: Python
Classifier: Programming Language :: Python :: 3
Classifier: Programming Language :: Python :: 3 :: Only
Classifier: Programming Language :: Python :: 3.10
Classifier: Programming Language :: Python :: 3.11
Classifier: Programming Language :: Python :: 3.12
Classifier: Programming Language :: Python :: 3.13
Classifier: Topic :: Internet :: WWW/HTTP
Classifier: Topic :: Internet :: WWW/HTTP :: Dynamic Content
Classifier: Topic :: Software Development :: Libraries :: Python Modules
Classifier: Topic :: System :: Logging
Requires-Python: >=3.10
License-File: LICENSE
Requires-Dist: django>=4.0.0
Requires-Dist: requests>=2.25.0
Dynamic: license-file
